casual_mcp/__init__.py
casual_mcp/cli.py
casual_mcp/logging.py
casual_mcp/main.py
casual_mcp/mcp_tool_chat.py
casual_mcp/utils.py
casual_mcp/models/__init__.py
casual_mcp/models/config.py
casual_mcp/models/generation_error.py
casual_mcp/models/mcp_server_config.py
casual_mcp/models/messages.py
casual_mcp/models/model_config.py
casual_mcp/models/tool_call.py
casual_mcp/providers/__init__.py
casual_mcp/providers/abstract_provider.py
casual_mcp/providers/ollama_provider.py
casual_mcp/providers/openai_provider.py
casual_mcp/providers/provider_factory.py
casual_mcp-0.4.0.dist-info/licenses/LICENSE
casual_mcp-0.4.0.dist-info/METADATA
casual_mcp-0.4.0.dist-info/WHEEL
casual_mcp-0.4.0.dist-info/entry_points.txt
casual_mcp-0.4.0.dist-info/top_level.txt
casual_mcp-0.4.0.dist-info/RECORD
