Metadata-Version: 2.4
Name: casual-mcp
Version: 0.4.0
Summary: Multi-server MCP client for LLM tool orchestration
Author: Alex Stansfield
License: MIT
Project-URL: Homepage, https://github.com/AlexStansfield/casual-mcp
Project-URL: Repository, https://github.com/AlexStansfield/casual-mcp
Project-URL: Issue Tracker, https://github.com/AlexStansfield/casual-mcp/issues
Requires-Python: >=3.10
License-File: LICENSE
Requires-Dist: dateparser>=1.2.1
Requires-Dist: fastapi>=0.115.12
Requires-Dist: fastmcp>=2.12.4
Requires-Dist: jinja2>=3.1.6
Requires-Dist: ollama>=0.4.8
Requires-Dist: openai>=1.78.0
Requires-Dist: python-dotenv>=1.1.0
Requires-Dist: requests>=2.32.3
Requires-Dist: rich>=14.0.0
Requires-Dist: typer>=0.19.2
Requires-Dist: uvicorn>=0.34.2
Provides-Extra: dev
Requires-Dist: ruff; extra == "dev"
Requires-Dist: black; extra == "dev"
Requires-Dist: mypy; extra == "dev"
Requires-Dist: pytest; extra == "dev"
Requires-Dist: coverage; extra == "dev"
Dynamic: license-file
